{
    "id": "elem.6.1",
    "n": 1,
    "type": "proposition",
    "enunciation": "`Triangles and parallelograms which are under the same height are to one another as their bases`.",
    "proof": [
        {
            "text": "Let `ABC`, `ACD` be triangles and `EC`, `CF` parallelograms under the same height; I say that, as the base `BC` is to the base `CD`, so is the triangle `ABC` to the triangle `ACD`, and the parallelogram `EC` to the parallelogram `CF`.",
            "refs": [],
            "emphs": [
                "ABC",
                "ACD",
                "EC",
                "CF",
                "BC",
                "CD",
                "ABC",
                "ACD",
                "EC",
                "CF"
            ]
        },
        {
            "text": "For let `BD` be produced in both directions to the points `H`, `L` and let [any number of straight lines] `BG`, `GH` be made equal to the base `BC`, and any number of straight lines `DK`, `KL` equal to the base `CD`; let `AG`, `AH`, `AK`, `AL` be joined.",
            "refs": [],
            "emphs": [
                "BD",
                "H",
                "L",
                "BG",
                "GH",
                "BC",
                "DK",
                "KL",
                "CD",
                "AG",
                "AH",
                "AK",
                "AL"
            ]
        },
        {
            "text": "Then, since `CB`, `BG`, `GH` are equal to one another, > the triangles `ABC`, `AGB`, `AHG` are also equal to one another. [elem.1.38]",
            "refs": [],
            "emphs": [
                "CB",
                "BG",
                "GH"
            ]
        },
        {
            "text": "Therefore, whatever multiple the base `HC` is of the base `BC`, that multiple also is the triangle `AHC` of the triangle `ABC`.",
            "refs": [],
            "emphs": [
                "HC",
                "BC",
                "AHC",
                "ABC"
            ]
        },
        {
            "text": "For the same reason, whatever multiple the base `LC` is of the base `CD`, that multiple also is the triangle `ALC` of the triangle `ACD`; and, if the base `HC` is equal to the base `CL`, the triangle `AHC` is also equal to the triangle `ACL`, [elem.1.38] if the base `HC` is in excess of the base `CL`, the triangle `AHC`\n       is also in excess of the triangle `ACL`, and, if less, less.",
            "refs": [
                "elem.1.38"
            ],
            "emphs": [
                "LC",
                "CD",
                "ALC",
                "ACD",
                "HC",
                "CL",
                "AHC",
                "ACL",
                "HC",
                "CL",
                "AHC",
                "ACL"
            ]
        },
        {
            "text": "Thus, there being four magnitudes, two bases `BC`, `CD` and two triangles `ABC`, `ACD`, equimultiples have been taken of the base `BC` and the triangle `ABC`, namely the base `HC` and the triangle `AHC`, and of the base `CD` and the triangle `ADC` other, chance, equimultiples, namely the base `LC` and the triangle `ALC`; > and it has been proved that, if the base `HC` is in excess of the base `CL`, the triangle `AHC`\n       is also in excess of the triangle `ALC`; if equal, equal; and, if less, less.",
            "refs": [],
            "emphs": [
                "BC",
                "CD",
                "ABC",
                "ACD",
                "BC",
                "ABC",
                "HC",
                "AHC",
                "CD",
                "ADC",
                "LC",
                "ALC",
                "HC",
                "CL",
                "AHC",
                "ALC"
            ]
        },
        {
            "text": "Therefore, as the base `BC` is to the base `CD`, so is the triangle `ABC` to the triangle `ACD`. [elem.5.def.5]",
            "refs": [
                "elem.5.def.5"
            ],
            "emphs": [
                "BC",
                "CD",
                "ABC",
                "ACD"
            ]
        },
        {
            "text": "Next, since the parallelogram `EC` is double of the triangle `ABC`, [elem.1.41] and the parallelogram `FC` is double of the triangle `ACD`, while parts have the same ratio as the same multiples of them, [elem.5.15] therefore, as the triangle `ABC` is to the triangle `ACD`, so is the parallelogram `EC` to the parallelogram `FC`.",
            "refs": [
                "elem.1.41",
                "elem.5.15"
            ],
            "emphs": [
                "EC",
                "ABC",
                "FC",
                "ACD",
                "ABC",
                "ACD",
                "EC",
                "FC"
            ]
        },
        {
            "text": "Since, then, it was proved that, as the base `BC` is to `CD`, so is the triangle `ABC` to the triangle `ACD`, and, as the triangle `ABC` is to the triangle `ACD`, so is the parallelogram `EC` to the parallelogram `CF`, therefore also, as the base `BC` is to the base `CD`, so is the parallelogram `EC` to the parallelogram `FC`. [elem.5.11]",
            "refs": [
                "elem.5.11"
            ],
            "emphs": [
                "BC",
                "CD",
                "ABC",
                "ACD",
                "ABC",
                "ACD",
                "EC",
                "CF",
                "BC",
                "CD",
                "EC",
                "FC"
            ]
        },
        {
            "text": "Therefore etc. Q. E. D.",
            "refs": [],
            "emphs": []
        }
    ]
}