{
    "id": "elem.1.22",
    "n": 22,
    "type": "proposition",
    "enunciation": "Out of three straight lines, which are equal to three given straight lines, to construct a triangle: thus it is necessary that two of the straight lines taken together in any manner should be greater than the remaining one. [elem.1.20]",
    "proof": [
        {
            "text": "Let the three given straight lines be `A`, `B`, `C`, and of these let two taken together in any manner be greater than the remaining one, namely `A`, `B` greater than `C`,  and `B`, `C` greater than `A`; thus it is required to construct a triangle out of straight lines equal to `A`, `B`, `C`.",
            "refs": [],
            "emphs": [
                "A",
                "B",
                "C",
                "A",
                "B",
                "C",
                "B",
                "C",
                "A",
                "A",
                "B",
                "C"
            ]
        },
        {
            "text": "Let there be set out a straight line `DE`, terminated at `D` but of infinite length in the direction of `E`, and let `DF` be made equal to `A`, `FG` equal to `B`, and `GH` equal to `C`. [elem.1.3]",
            "refs": [
                "elem.1.3"
            ],
            "emphs": [
                "DE",
                "D",
                "E",
                "DF",
                "A",
                "FG",
                "B",
                "GH",
                "C"
            ]
        },
        {
            "text": "With centre `F` and distance `FD` let the circle `DKL` be described; again, with centre `G` and distance `GH` let the circle `KLH` be described; and let `KF`, `KG` be joined;",
            "refs": [],
            "emphs": [
                "F",
                "FD",
                "DKL",
                "G",
                "GH",
                "KLH",
                "KF",
                "KG"
            ]
        },
        {
            "text": "I say that the triangle `KFG` has been constructed out of three straight lines equal to `A`, `B`, `C`.",
            "refs": [],
            "emphs": [
                "KFG",
                "A",
                "B",
                "C"
            ]
        },
        {
            "text": "For, since the point `F` is the centre of the circle `DKL`,",
            "refs": [],
            "emphs": [
                "F",
                "DKL"
            ]
        },
        {
            "text": "But `FD` is equal to `A`;",
            "refs": [],
            "emphs": [
                "FD",
                "A"
            ]
        },
        {
            "text": "Again, since the point `G` is the centre of the circle `LKH`,",
            "refs": [],
            "emphs": [
                "G",
                "LKH"
            ]
        },
        {
            "text": "But `GH` is equal to `C`;  therefore the three straight lines `KF`, `FG`, `GK` are equal to the three straight lines `A`, `B`, `C`.",
            "refs": [],
            "emphs": [
                "GH",
                "C",
                "KF",
                "FG",
                "GK",
                "A",
                "B",
                "C"
            ]
        },
        {
            "text": "Therefore out of the three straight lines `KF`, `FG`, `GK`, which are equal to the three given straight lines `A`, `B`, `C`, the triangle `KFG` has been constructed.",
            "refs": [],
            "emphs": [
                "KF",
                "FG",
                "GK",
                "A",
                "B",
                "C",
                "KFG"
            ]
        }
    ]
}