{
    "id": "elem.12.6",
    "n": 6,
    "type": "proposition",
    "proof": [
        {
            "text": "Let there be pyramids of the same height of which the polygons ,  are the bases and the points ,  the vertices; I say that, as the base  is to the base , so is the pyramid  to the pyramid .",
            "refs": [],
            "emphs": []
        },
        {
            "text": "For let , , ,  be joined.",
            "refs": [],
            "emphs": []
        },
        {
            "text": "Since then ,  are two pyramids which have triangular bases and equal height, they are to one another as the bases; [elem.12.5] therefore, as the base  is to the base , so is the pyramid  to the pyramid .",
            "refs": [
                "elem.12.5"
            ],
            "emphs": []
        },
        {
            "text": "And, , as the base  is to the base , so is the pyramid  to the pyramid . [elem.5.18]",
            "refs": [
                "elem.5.18"
            ],
            "emphs": []
        },
        {
            "text": "But also, as the base  is to the base , so is the pyramid  to the pyramid . [elem.12.5]",
            "refs": [
                "elem.12.5"
            ],
            "emphs": []
        },
        {
            "text": "Therefore, , as the base  is to the base , so is the pyramid  to the pyramid . [elem.5.22]",
            "refs": [
                "elem.5.22"
            ],
            "emphs": []
        },
        {
            "text": "And again , as the base  is to the base , so is the pyramid  to the pyramid . [elem.5.18]",
            "refs": [
                "elem.5.18"
            ],
            "emphs": []
        },
        {
            "text": "Similarly also it can be proved that, as the base  is to the base , so is the pyramid  to the pyramid .",
            "refs": [],
            "emphs": []
        },
        {
            "text": "And, since ,  are two pyramids which have triangular bases and equal height, therefore, as the base  is to the base , so is the pyramid  to the pyramid . [elem.12.5]",
            "refs": [
                "elem.12.5"
            ],
            "emphs": []
        },
        {
            "text": "But, as the base  is to the base , so was the pyramid  to the pyramid .",
            "refs": [],
            "emphs": []
        },
        {
            "text": "Therefore also, , as the base  is to the base , so is the pyramid  to the pyramid . [elem.5.22]",
            "refs": [
                "elem.5.22"
            ],
            "emphs": []
        },
        {
            "text": "But further, as the base  is to the base , so also was the pyramid  to the pyramid .",
            "refs": [],
            "emphs": []
        },
        {
            "text": "Therefore also, , as the base  is to the base , so is the pyramid  to the pyramid . [elem.5.22] Q. E. D.",
            "refs": [
                "elem.5.22"
            ],
            "emphs": []
        }
    ]
}