{
    "elem.3.9": {
        "id": "elem.3.9",
        "n": 9,
        "type": "proposition",
        "enunciation": "`If a point be taken within a circle`, `and more than two equal straight lines fall from the point on the circle`, `the point taken is the centre of the circle`.",
        "proof": [
            {
                "text": "Let `ABC` be a circle and `D` a point within it, and from `D` let more than two equal straight lines, namely `DA`, `DB`, `DC`, fall on the circle `ABC`; I say that the point `D` is the centre of the circle `ABC`.",
                "refs": [],
                "emphs": [
                    "ABC",
                    "D",
                    "D",
                    "DA",
                    "DB",
                    "DC",
                    "ABC",
                    "D",
                    "ABC"
                ]
            },
            {
                "text": "For let `AB`, `BC` be joined and bisected at the points `E`, `F`, and let `ED`, `FD` be joined and drawn through to the points `G`, `K`, `H`, `L`.",
                "refs": [],
                "emphs": [
                    "AB",
                    "BC",
                    "E",
                    "F",
                    "ED",
                    "FD",
                    "G",
                    "K",
                    "H",
                    "L"
                ]
            },
            {
                "text": "Then, since `AE` is equal to `EB`, and `ED` is common, > the two sides `AE`, `ED` are equal to the two sides `BE`, `ED`; and the base `DA` is equal to the base `DB`; > therefore the angle `AED` is equal to the angle `BED`. [elem.1.8]",
                "refs": [],
                "emphs": [
                    "AE",
                    "EB",
                    "ED",
                    "DA",
                    "DB"
                ]
            },
            {
                "text": "Therefore each of the angles `AED`, `BED` is right; [elem.1.def.10] therefore `GK` cuts `AB` into two equal parts and at right angles.",
                "refs": [
                    "elem.1.def.10"
                ],
                "emphs": [
                    "AED",
                    "BED",
                    "GK",
                    "AB"
                ]
            },
            {
                "text": "And since, if in a circle a straight line cut a straight line into two equal parts and at right angles, the centre of the circle is on the cutting straight line, [elem.3.1.p.1] > the centre of the circle is on `GK`.",
                "refs": [
                    "elem.3.1.p.1"
                ],
                "emphs": []
            },
            {
                "text": "For the same reason > the centre of the circle `ABC` is also on `HL`.",
                "refs": [],
                "emphs": []
            },
            {
                "text": "And the straight lines `GK`, `HL` have no other point common but the point `D`; > therefore the point `D` is the centre of the circle `ABC`.",
                "refs": [],
                "emphs": [
                    "GK",
                    "HL",
                    "D"
                ]
            },
            {
                "text": "Therefore etc. Q. E. D.",
                "refs": [],
                "emphs": []
            }
        ]
    }
}